smstool/__init__.py
smstool/sms_tool.py
smstool/auth/__init__.py
smstool/auth/auth.py
smstool/https/__init__.py
smstool/https/abstract_func.py
smstool/https/api_request.py
smstool/utils/__init__.py
smstool/utils/exceptions.py
smstool/utils/logger.py
smstool/utils/values.py
sms_tool-0.0.1.dist-info/LICENSE.txt
sms_tool-0.0.1.dist-info/METADATA
sms_tool-0.0.1.dist-info/WHEEL
sms_tool-0.0.1.dist-info/top_level.txt
sms_tool-0.0.1.dist-info/RECORD
